MANIFEST.in
README.md
setup.py
mmipylint/__init__.py
mmipylint/main.py
mothermayi_pylint.egg-info/PKG-INFO
mothermayi_pylint.egg-info/SOURCES.txt
mothermayi_pylint.egg-info/dependency_links.txt
mothermayi_pylint.egg-info/entry_points.txt
mothermayi_pylint.egg-info/requires.txt
mothermayi_pylint.egg-info/top_level.txt