Metadata-Version: 1.0
Name: mothermayi-pylint
Version: 0.5
Summary: The pylint plugin for mothermayi
Home-page: https://github.com/EliRibble/mothermayi-pylint
Author: Eli Ribble
Author-email: junk@theribbles.org
License: UNKNOWN
Platform: UNKNOWN
